datawrap.py
datawrap-1.0.0.dist-info/licenses/LICENSE
datawrap-1.0.0.dist-info/METADATA
datawrap-1.0.0.dist-info/WHEEL
datawrap-1.0.0.dist-info/top_level.txt
datawrap-1.0.0.dist-info/RECORD
