Metadata-Version: 2.4
Name: datawrap
Version: 1.0.0
Summary: Wrap dictionaries of data for quick traversal and useful messages when data doesn't match expectations.
Author-email: Nathan Shearer <shearern@gmail.com>
License-Expression: MIT AND (Apache-2.0 OR BSD-2-Clause)
Project-URL: Repository, https://gitlab.com/shearern/datawrap
Requires-Python: >=3.7
License-File: LICENSE
Dynamic: license-file
